{
  "id": "mining",
  "title": "Deep Mining",
  "icon": "diamond_ore",
  "description": "Master the depths and gather precious resources",
  "tasks": [
    { "id": "mi-1", "text": "Dig to Y level -59", "icon": "deepslate", "description": "Deepest mining level" },
    { "id": "mi-2", "text": "Mine 64 coal", "icon": "coal", "description": "Fuel stockpile" },
    { "id": "mi-3", "text": "Mine 64 raw iron", "icon": "raw_iron", "description": "Iron stockpile" },
    { "id": "mi-4", "text": "Mine 64 raw copper", "icon": "raw_copper", "description": "Copper stockpile" },
    { "id": "mi-5", "text": "Mine 32 raw gold", "icon": "raw_gold", "description": "Gold stockpile" },
    { "id": "mi-6", "text": "Mine 32 diamonds", "icon": "diamond", "description": "Precious gems" },
    { "id": "mi-7", "text": "Mine 64 lapis lazuli", "icon": "lapis_lazuli", "description": "For enchanting" },
    { "id": "mi-8", "text": "Mine 64 redstone", "icon": "redstone", "description": "For circuits" },
    { "id": "mi-9", "text": "Mine emeralds", "icon": "emerald", "description": "Found in mountains" },
    { "id": "mi-10", "text": "Find an amethyst geode", "icon": "amethyst_shard", "description": "Purple crystal cave" },
    { "id": "mi-11", "text": "Collect amethyst shards", "icon": "amethyst_shard", "description": "For tinted glass" },
    { "id": "mi-12", "text": "Craft a spyglass", "icon": "spyglass", "description": "Zoom in far" },
    { "id": "mi-13", "text": "Craft tinted glass", "icon": "tinted_glass", "description": "Blocks light, see-through" },
    { "id": "mi-14", "text": "Mine obsidian", "icon": "obsidian", "description": "For Nether portal" },
    { "id": "mi-15", "text": "Collect 10 obsidian", "icon": "obsidian", "description": "Enough for a portal" },
    { "id": "mi-16", "text": "Find a lush cave", "icon": "glow_berries", "description": "Azalea above ground" },
    { "id": "mi-17", "text": "Collect glow berries", "icon": "glow_berries", "description": "Light-emitting food" },
    { "id": "mi-18", "text": "Collect dripleaf", "icon": "big_dripleaf", "description": "Tilting platform" },
    { "id": "mi-19", "text": "Collect moss blocks", "icon": "moss_block", "description": "Green decoration" },
    { "id": "mi-20", "text": "Collect spore blossoms", "icon": "spore_blossom", "description": "Ceiling flower" },
    { "id": "mi-21", "text": "Find a dripstone cave", "icon": "pointed_dripstone", "description": "Stalagmites and stalactites" },
    { "id": "mi-22", "text": "Collect pointed dripstone", "icon": "pointed_dripstone", "description": "Sharp decorations" },
    { "id": "mi-23", "text": "Build a lava drip system", "icon": "lava_bucket", "description": "Renewable lava" },
    { "id": "mi-24", "text": "Find a mineshaft", "icon": "chest_minecart", "description": "Abandoned mining tunnels" },
    { "id": "mi-25", "text": "Collect mineshaft loot", "icon": "chest_minecart", "description": "Rare items in chests" },
    { "id": "mi-26", "text": "Kill a cave spider", "icon": "spider_eye", "description": "Mineshaft enemy" },
    { "id": "mi-27", "text": "Find a dungeon", "icon": "spawner", "description": "Monster spawner room" },
    { "id": "mi-28", "text": "Collect dungeon loot", "icon": "golden_apple", "description": "Rare chest items" },
    { "id": "mi-29", "text": "Find a stronghold", "icon": "ender_eye", "description": "End portal location" },
    { "id": "mi-30", "text": "Mine deepslate", "icon": "deepslate", "description": "Deep stone variant" },
    { "id": "mi-31", "text": "Craft deepslate bricks", "icon": "deepslate_bricks", "description": "Dark building block" },
    { "id": "mi-32", "text": "Mine tuff", "icon": "tuff", "description": "Volcanic rock" },
    { "id": "mi-33", "text": "Mine calcite", "icon": "calcite", "description": "White stone from geodes" },
    { "id": "mi-34", "text": "Build a strip mine at Y -59", "icon": "diamond_ore", "description": "Optimal diamond level" },
    { "id": "mi-35", "text": "Build a branch mine", "icon": "torch", "description": "Efficient mining pattern" },
    { "id": "mi-36", "text": "Set up mining base underground", "icon": "chest", "description": "Storage and furnaces" },
    { "id": "mi-37", "text": "Find ancient debris", "icon": "ancient_debris", "description": "Nether-only, but prep here" },
    { "id": "mi-38", "text": "Collect glow lichen", "icon": "glow_lichen", "description": "Cave light source" }
  ]
}
